esp_trainer/__init__.py
esp_trainer/__main__.py
esp_trainer/__version__.py
esp_trainer/cli.py
esp_trainer-1.0.1.dist-info/LICENSE
esp_trainer-1.0.1.dist-info/METADATA
esp_trainer-1.0.1.dist-info/WHEEL
esp_trainer-1.0.1.dist-info/entry_points.txt
esp_trainer-1.0.1.dist-info/top_level.txt
esp_trainer-1.0.1.dist-info/RECORD
