Metadata-Version: 2.1
Name: esp-trainer
Version: 1.0.1
Summary: ESP trainer that runs in your terminal
Home-page: https://github.com/dspacejs/cli-esp-trainer
Author: Daniel Spajic
Author-email: daniel@danieljs.tech
License: MIT
Platform: UNKNOWN
Classifier: License :: OSI Approved :: MIT License
Classifier: Programming Language :: Python :: 3
Classifier: Programming Language :: Python :: 3.8
Classifier: Topic :: Games/Entertainment
Requires-Python: >=3.8.2
Requires-Dist: colorama (>=0.4.3)
Requires-Dist: tabulate (>=0.8.7)
